pydantic_sweep/__init__.py
pydantic_sweep/_generation.py
pydantic_sweep/_model.py
pydantic_sweep/_model_diff.py
pydantic_sweep/_nested_dict.py
pydantic_sweep/_utils.py
pydantic_sweep/cli.py
pydantic_sweep/convert.py
pydantic_sweep/py.typed
pydantic_sweep/testing.py
pydantic_sweep/types.py
pydantic_sweep-0.3.8.dist-info/WHEEL
pydantic_sweep-0.3.8.dist-info/METADATA
pydantic_sweep-0.3.8.dist-info/RECORD
