Metadata-Version: 2.4
Name: pydantic-sweep
Version: 0.3.8
Summary: Programmatic parameter sweeps for pydantic.
Author: Felix Berkenkamp
License-Expression: MPL-2.0
Classifier: Operating System :: OS Independent
Classifier: License :: OSI Approved :: Mozilla Public License 2.0 (MPL 2.0)
Classifier: Programming Language :: Python
Classifier: Programming Language :: Python :: 3.10
Classifier: Programming Language :: Python :: 3.11
Classifier: Programming Language :: Python :: 3.12
Classifier: Programming Language :: Python :: 3.13
Classifier: Programming Language :: Python :: 3.14
Classifier: Programming Language :: Python :: 3 :: Only
Classifier: Topic :: Software Development :: Libraries
Classifier: Typing :: Typed
Requires-Dist: more-itertools~=10.1
Requires-Dist: pydantic~=2.5
Requires-Dist: tomli-w>=1.0,<2
Requires-Dist: tomli>=2.0.0 ; python_full_version < '3.11'
Requires-Dist: pyyaml>=5.0.0 ; extra == 'yaml'
Requires-Python: >=3.10
Project-URL: Documentation, https://pydantic-sweep.readthedocs.io
Project-URL: Releases, https://github.com/befelix/pydantic_sweep/releases
Project-URL: Repository, https://github.com/befelix/pydantic_sweep
Provides-Extra: yaml
